mcp_jamie_test2/__init__.py
mcp_jamie_test2/server.py
mcp_jamie_test2-1.0.9.dist-info/METADATA
mcp_jamie_test2-1.0.9.dist-info/WHEEL
mcp_jamie_test2-1.0.9.dist-info/entry_points.txt
mcp_jamie_test2-1.0.9.dist-info/RECORD
