Metadata-Version: 2.4
Name: mcp-jamie-test2
Version: 1.0.9
Summary: MCP server 测试使用
Requires-Python: >=3.13
Requires-Dist: httpx>=0.28.1
Requires-Dist: mcp>=1.6.0
